{
"background": 5,
"dimensions": [ 3000, 800 ],
"somni": {
	"pos": [ 5, 5 ]
},
"phobia": {
		"pos": [ 84, 19 ]
},
"goal": {
	"pos": [ 49, 14 ]
},
"objects": [
	{
		"type": 3,
		"assetName": "shared:all",
		"positions": [
			[ 4, 4, 8, 1 ],
			[ 14, 7, 6, 1 ],
			[ 22, 12, 6, 1 ],
			[ 36, 12, 6, 1 ],
			[ 59, 20, 10, 1 ],
			[ 63, 21, 1, 7 ],
			[ 77, 18, 10, 1 ],
			[ 47, 13, 6, 1 ]
		],
		"property": 1,
		"paths": [
			[ 4, 4 ],
			[ 14, 7 ],
			[ 22, 12 ],
			[ 36, 12 ],
			[ 59, 20 ],
			[ 63, 21 ],
			[ 77, 18 ],
			[ 47, 13 ]
		]
	},
	{
		"type": 1,
		"assetName": 1,
		"positions": [
			[ 17, 17, 1, 1 ]
		],
		"property": 1,
		"paths": [
			[ 17, 17 ]
		]
	},
	{
		"type": 2,
		"assetName": 5,
		"positions": [
			[ 73, 17, 1, 1 ]
		],
		"property": 1,
		"paths": [
			[ 73, 17 ]
		]
	}
]
}