{
	"background": 5,
	"dimensions": [ 2500, 800 ],
	"somni": {
		"pos": [ 6, 6 ]
	},
	"phobia": {
		"pos": [ 61, 18 ]
	},
	"goal": {
		"pos": [ 39, 12 ]
	},
	"objects": [
		{
			"type": 3,
			"assetName": "shared:all",
			"positions": [
				[ 4, 5, 8, 1 ],
				[ 12, 8, 3, 1 ],
				[ 15, 11, 3, 1 ],
				[ 20, 11, 5, 1 ],
				[ 27, 8, 5, 1 ],
				[ 35, 11, 10, 1 ],
				[ 46, 17, 5, 1 ],
				[ 54, 17, 8, 1 ]
			],
			"property": 1,
			"paths": [
				[ 4, 5 ],
				[ 12, 8 ],
				[ 15, 11 ],
				[ 20, 11 ],
				[ 27, 8 ],
				[ 35, 11 ],
				[ 46, 17 ],
				[ 54, 17 ]
			]
		},
		{
			"type": 1,
			"assetName": 9,
			"positions": [
				[ 35, 18, 1, 1 ]
			],
			"property": 1,
			"paths": [
				[ 35, 18 ]
			]
		},
		{
			"type": 2,
			"assetName": 11,
			"positions": [
				[ 40, 6, 1, 1 ]
			],
			"property": 1,
			"paths": [
				[ 40, 7 ]
			]
		}
	]
}