{
"background": 1,
"dimensions": [ 1400, 1400 ],
"somni": {
	"pos": [ 17, 13 ]
},
"phobia": {
	"pos": [ 20, 13 ]
},
"goal": {
	"pos": [ 33, 37 ]
},
"objects": [
	{
		"type": 3,
		"assetName": "shared:all",
		"positions": [
			[ 15, 12, 40, 1 ],
			[ 28, 19, 2, 2 ],
			[ 20, 23, 2, 2 ],
			[ 24, 24, 2, 2 ],
			[ 17, 21, 1, 2 ],
			[ 18, 20, 1, 2 ],
			[ 47, 22, 2, 2 ],
			[ 43, 24, 2, 2 ],
			[ 47, 28, 2, 2 ]
		],
		"property": 1,
		"paths": [
			[ 15, 12 ],
			[ 28, 19 ],
			[ 20, 23 ],
			[ 24, 24 ],
			[ 17, 21 ],
			[ 18, 20 ],
			[ 47, 22 ],
			[ 43, 24 ],
			[ 47, 28 ]
		]
	},
	{
		"type": 2,
		"assetName": "shared:dark",
		"positions": [
			[ 24, 13, 3, 1 ],
			[ 23, 14, 3, 1 ],
			[ 22, 15, 3, 1 ],
			[ 22, 16, 3, 1 ],
			[ 22, 17, 3, 1 ],
			[ 23, 18, 3, 1 ],
			[ 24, 19, 3, 1 ],
			[ 40, 19, 4, 1 ],
			[ 47, 19, 5, 1 ],
			[ 48, 20, 4, 1 ],
			[ 40, 21, 12, 1 ],
			[ 40, 18, 3, 1 ],
			[ 49, 18, 3, 1 ],
			[ 41, 20, 4, 1 ],
			[ 49, 22, 2, 1 ],
			[ 49, 23, 3, 1 ],
			[ 40, 23, 7, 1 ],
			[ 49, 24, 3, 1 ],
			[ 49, 25, 1, 1 ],
			[ 41, 25, 2, 1 ],
			[ 40, 24, 3, 1 ],
			[ 41, 22, 6, 1 ],
			[ 45, 24, 4, 1 ],
			[ 45, 25, 4, 1 ],
			[ 40, 26, 11, 1 ],
			[ 42, 27, 8, 1 ],
			[ 47, 31, 3, 1 ],
			[ 49, 28, 3, 1 ],
			[ 49, 29, 2, 1 ],
			[ 45, 30, 5, 1 ],
			[ 17, 32, 8, 1 ],
			[ 14, 33, 8, 1 ],
			[ 14, 44, 8, 1 ],
			[ 17, 45, 8, 1 ],
			[ 29, 31, 3, 1 ],
			[ 31, 32, 2, 1 ],
			[ 18, 31, 8, 1 ],
			[ 20, 30, 11, 1 ],
			[ 12, 42, 8, 2 ],
			[ 12, 40, 7, 2 ],
			[ 12, 38, 6, 2 ],
			[ 12, 34, 8, 2 ],
			[ 12, 36, 7, 2 ],
			[ 18, 46, 8, 1 ],
			[ 20, 47, 11, 1 ],
			[ 29, 46, 3, 1 ],
			[ 31, 45, 2, 1 ],
			[ 34, 43, 1, 1 ],
			[ 34, 34, 1, 1 ],
			[ 32, 44, 2, 1 ],
			[ 32, 33, 2, 1 ],
			[ 48, 32, 2, 1 ],
			[ 43, 28, 4, 1 ],
			[ 44, 29, 3, 1 ]
		],
		"property": 1,
		"paths": [
			[ 24, 13 ],
			[ 23, 14 ],
			[ 22, 15 ],
			[ 22, 16 ],
			[ 22, 17 ],
			[ 23, 18 ],
			[ 24, 19 ],
			[ 40, 19 ],
			[ 47, 19 ],
			[ 48, 20 ],
			[ 40, 21 ],
			[ 40, 18 ],
			[ 49, 18 ],
			[ 41, 20 ],
			[ 49, 22 ],
			[ 49, 23 ],
			[ 40, 23 ],
			[ 49, 24 ],
			[ 49, 25 ],
			[ 41, 25 ],
			[ 40, 24 ],
			[ 41, 22 ],
			[ 45, 24 ],
			[ 45, 25 ],
			[ 40, 26 ],
			[ 42, 27 ],
			[ 47, 31 ],
			[ 49, 28 ],
			[ 49, 29 ],
			[ 45, 30 ],
			[ 17, 32 ],
			[ 14, 33 ],
			[ 14, 44 ],
			[ 17, 45 ],
			[ 29, 31 ],
			[ 31, 32 ],
			[ 18, 31 ],
			[ 20, 30 ],
			[ 12, 42 ],
			[ 12, 40 ],
			[ 12, 38 ],
			[ 12, 34 ],
			[ 12, 36 ],
			[ 18, 46 ],
			[ 20, 47 ],
			[ 29, 46 ],
			[ 31, 45 ],
			[ 34, 43 ],
			[ 34, 34 ],
			[ 32, 44 ],
			[ 32, 33 ],
			[ 48, 32 ],
			[ 43, 28 ],
			[ 44, 29 ]
		]
	},
	{
		"type": 1,
		"assetName": "shared:light",
		"positions": [
			[ 18, 18, 5, 1 ],
			[ 17, 19, 7, 1 ],
			[ 26, 18, 5, 1 ],
			[ 21, 26, 9, 1 ],
			[ 44, 13, 3, 1 ],
			[ 45, 14, 3, 1 ],
			[ 46, 15, 3, 1 ],
			[ 46, 16, 3, 1 ],
			[ 45, 17, 3, 1 ],
			[ 44, 18, 3, 1 ],
			[ 44, 19, 3, 1 ],
			[ 45, 20, 3, 1 ],
			[ 39, 34, 2, 1 ],
			[ 16, 24, 4, 1 ],
			[ 16, 23, 4, 1 ],
			[ 15, 20, 3, 1 ],
			[ 14, 21, 3, 1 ],
			[ 15, 22, 2, 1 ],
			[ 30, 19, 4, 1 ],
			[ 27, 19, 1, 1 ],
			[ 19, 20, 9, 1 ],
			[ 30, 20, 4, 1 ],
			[ 18, 22, 17, 1 ],
			[ 19, 21, 16, 1 ],
			[ 17, 25, 7, 1 ],
			[ 22, 24, 2, 1 ],
			[ 26, 25, 5, 1 ],
			[ 26, 24, 6, 1 ],
			[ 22, 23, 11, 1 ],
			[ 28, 42, 2, 1 ],
			[ 39, 43, 2, 1 ],
			[ 31, 35, 6, 1 ],
			[ 31, 42, 6, 1 ],
			[ 36, 41, 2, 1 ],
			[ 36, 36, 2, 1 ],
			[ 37, 40, 1, 1 ],
			[ 37, 37, 1, 1 ],
			[ 38, 37, 1, 4 ],
			[ 27, 43, 2, 1 ],
			[ 38, 42, 2, 1 ],
			[ 38, 35, 2, 1 ],
			[ 40, 39, 2, 1 ],
			[ 42, 38, 2, 1 ],
			[ 44, 39, 2, 1 ],
			[ 26, 38, 2, 1 ],
			[ 24, 39, 2, 1 ],
			[ 22, 38, 2, 1 ],
			[ 28, 35, 2, 1 ],
			[ 27, 34, 2, 1 ],
			[ 34, 45, 1, 1 ],
			[ 33, 46, 1, 1 ],
			[ 33, 32, 1, 1 ],
			[ 34, 31, 1, 1 ],
			[ 27, 39, 2, 1 ],
			[ 30, 36, 2, 1 ],
			[ 30, 37, 1, 1 ],
			[ 46, 38, 2, 1 ],
			[ 20, 39, 2, 1 ],
			[ 18, 38, 2, 1 ],
			[ 30, 41, 1, 1 ],
			[ 29, 37, 1, 2 ],
			[ 39, 38, 2, 1 ],
			[ 48, 39, 2, 1 ]
		],
		"property": 1,
		"paths": [
			[ 18, 18 ],
			[ 17, 19 ],
			[ 26, 18 ],
			[ 21, 26 ],
			[ 44, 13 ],
			[ 45, 14 ],
			[ 46, 15 ],
			[ 46, 16 ],
			[ 45, 17 ],
			[ 44, 18 ],
			[ 44, 19 ],
			[ 45, 20 ],
			[ 39, 34 ],
			[ 16, 24 ],
			[ 16, 23 ],
			[ 15, 20 ],
			[ 14, 21 ],
			[ 15, 22 ],
			[ 30, 19 ],
			[ 27, 19 ],
			[ 19, 20 ],
			[ 30, 20 ],
			[ 18, 22 ],
			[ 19, 21 ],
			[ 17, 25 ],
			[ 22, 24 ],
			[ 26, 25 ],
			[ 26, 24 ],
			[ 22, 23 ],
			[ 28, 42 ],
			[ 39, 43 ],
			[ 31, 35 ],
			[ 31, 42 ],
			[ 36, 41 ],
			[ 36, 36 ],
			[ 37, 40 ],
			[ 37, 37 ],
			[ 38, 37 ],
			[ 27, 43 ],
			[ 38, 42 ],
			[ 38, 35 ],
			[ 40, 39 ],
			[ 42, 38 ],
			[ 44, 39 ],
			[ 26, 38 ],
			[ 24, 39 ],
			[ 22, 38 ],
			[ 28, 35 ],
			[ 27, 34 ],
			[ 34, 45 ],
			[ 33, 46 ],
			[ 33, 32 ],
			[ 34, 31 ],
			[ 27, 39 ],
			[ 30, 36 ],
			[ 30, 37 ],
			[ 46, 38 ],
			[ 20, 39 ],
			[ 18, 38 ],
			[ 30, 41 ],
			[ 29, 37 ],
			[ 39, 38 ],
			[ 48, 39 ]
		]
	}
]
}